hasts/plugins/__init__.py
hasts/plugins/version.py
hasts/plugins/manager/__init__.py
hasts/plugins/plugin/__init__.py
hasts/plugins/services/__init__.py
hasts/plugins/services/flaskapp.py
hasts_plugins-0.0.7.dist-info/LICENSE
hasts_plugins-0.0.7.dist-info/METADATA
hasts_plugins-0.0.7.dist-info/WHEEL
hasts_plugins-0.0.7.dist-info/top_level.txt
hasts_plugins-0.0.7.dist-info/RECORD
